README.md
datago/__init__.py
datago/datago.cpython-312-x86_64-linux-gnu.so
datago-2026.1.2.dist-info/METADATA
datago-2026.1.2.dist-info/WHEEL
datago-2026.1.2.dist-info/licenses/LICENSE
datago-2026.1.2.dist-info/RECORD
