Metadata-Version: 2.4
Name: datago
Version: 2026.1.2
Classifier: Programming Language :: Rust
Classifier: Programming Language :: Python :: Implementation :: CPython
Classifier: Programming Language :: Python :: Implementation :: PyPy
Classifier: Programming Language :: Python :: 3
Classifier: License :: OSI Approved :: MIT License
License-File: LICENSE
Summary: A high performance dataloader for Python, written in Rust
Author: Benjamin Lefaudeux, Roman Frigg
Author-email: Photoroom <team@photoroom.com>
Requires-Python: >=3.8
Project-URL: Homepage, https://github.com/photoroom/datago
Project-URL: Issues, https://github.com/photoroom/datago/issues
